Metadata-Version: 2.1
Name: cryptomsg
Version: 0.2.0
Summary: A simple python package to encrypt and decrypt messages with AES CBC mode.
Home-page: https://github.com/jacklinquan/cryptomsg
Author: Quan Lin
Author-email: jacklinquan@gmail.com
License: MIT
Platform: UNKNOWN
Classifier: Development Status :: 3 - Alpha
Classifier: License :: OSI Approved :: MIT License
Classifier: Programming Language :: Python :: 2
Classifier: Programming Language :: Python :: 2.7
Classifier: Programming Language :: Python :: 3
